toychain/__init__.py
toychain/__main__.py
toychain/blockchain.py
toychain/node.py
toychain-0.2.0.dist-info/entry_points.txt
toychain-0.2.0.dist-info/WHEEL
toychain-0.2.0.dist-info/METADATA
toychain-0.2.0.dist-info/RECORD
