Metadata-Version: 2.1
Name: toychain
Version: 0.2.0
Summary: A blockchain toy project, in Python
Home-page: https://github.com/fsoubelet/toychain
License: MIT
Author: Your Name
Author-email: you@example.com
Requires-Python: >=3.6,<4.0
Classifier: License :: OSI Approved :: MIT License
Classifier: Programming Language :: Python :: 3
Classifier: Programming Language :: Python :: 3.6
Classifier: Programming Language :: Python :: 3.7
Classifier: Programming Language :: Python :: 3.8
Requires-Dist: fastapi (>=0.55.1,<0.56.0)
Requires-Dist: loguru (>=0.4.1,<0.5.0)
Requires-Dist: requests (>=2.23.0,<3.0.0)
Requires-Dist: uvicorn (>=0.11.5,<0.12.0)
Project-URL: Repository, https://github.com/fsoubelet/toychain
